dynamod/__init__.py
dynamod/actionstack.py
dynamod/afterdist.py
dynamod/builder.py
dynamod/checks.py
dynamod/context.py
dynamod/core.py
dynamod/evaluation.py
dynamod/flexdot.py
dynamod/helper.py
dynamod/history.py
dynamod/model.py
dynamod/optimize.py
dynamod/parse_helper.py
dynamod/partition.py
dynamod/segop.py
dynamod/splitsys.py
dynamod/tracer.py
dynamod/parser/DynamodLexer.py
dynamod/parser/DynamodParser.py
dynamod/parser/DynamodVisitor.py
dynamod/parser/__init__.py
dynamod-0.9.8.dist-info/LICENSE
dynamod-0.9.8.dist-info/METADATA
dynamod-0.9.8.dist-info/WHEEL
dynamod-0.9.8.dist-info/top_level.txt
dynamod-0.9.8.dist-info/RECORD
