Metadata-Version: 2.1
Name: dynamod
Version: 0.9.8
Summary: build and run compartmental models in epidemiology
Home-page: https://github.com/andromed2/dynamod
Author: Andreas Neumann
Author-email: andromed@web.de
Classifier: Programming Language :: Python :: 3
Classifier: License :: OSI Approved :: GNU General Public License v3 (GPLv3)
Classifier: Operating System :: OS Independent
Requires-Python: >=3.6
License-File: LICENSE
Requires-Dist: gradescent (>=0.9.4)
Requires-Dist: recordtype
Requires-Dist: numpy
Requires-Dist: scipy
Requires-Dist: antlr4-python3-runtime (==4.9.2)
Requires-Dist: pandas
